djauto-1.2.3.dist-info/top_level.txt
djauto-1.2.3.dist-info/METADATA
djauto-1.2.3.dist-info/RECORD
djauto-1.2.3.dist-info/DESCRIPTION.rst
djauto-1.2.3.dist-info/WHEEL
djauto-1.2.3.dist-info/entry_points.txt
djauto-1.2.3.dist-info/metadata.json
djauto/auto.py
djauto/__init__.py
