Metadata-Version: 2.0
Name: djauto
Version: 1.2.3
Summary: Django project generator
Home-page: https://github.com/vikas-parashar/django-project-generator
Author: Vikas Parashar
Author-email: svnitvikas@gmai.com
License: MIT
Keywords: django,python,django-packages,packages
Platform: UNKNOWN
Classifier: Development Status :: 3 - Alpha
Classifier: Environment :: Web Environment
Classifier: Intended Audience :: Developers
Classifier: Operating System :: OS Independent
Classifier: Programming Language :: Python
Classifier: Topic :: Software Development :: Libraries :: Python Modules
Classifier: Natural Language :: English
Classifier: Programming Language :: Python :: 2.6
Classifier: Programming Language :: Python :: 2.7
Classifier: Framework :: Django
Classifier: License :: OSI Approved :: MIT License
